[
    {
        "title": "非穷尽列举",
        "link": "https://movie.douban.com/subject/37293378/?from=playing_poster",
        "image_url": "https://img9.doubanio.com/view/photo/s_ratio_poster/public/p2929789264.jpg",
        "score": "9.3",
        "region": "英国",
        "rank": 1
    },
    {
        "title": "暗黑新娘！",
        "link": "https://movie.douban.com/subject/36503073/?from=playing_poster",
        "image_url": "https://img1.doubanio.com/view/photo/s_ratio_poster/public/p2929036260.jpg",
        "score": "暂无评分",
        "region": "美国",
        "rank": 2
    },
    {
        "title": "夜王",
        "link": "https://movie.douban.com/subject/37375594/?from=playing_poster",
        "image_url": "https://img9.doubanio.com/view/photo/s_ratio_poster/public/p2929673775.jpg",
        "score": "7.8",
        "region": "中国大陆 中国香港",
        "rank": 3
    },
    {
        "title": "镖人：风起大漠",
        "link": "https://movie.douban.com/subject/36474027/?from=playing_poster",
        "image_url": "https://img9.doubanio.com/view/photo/s_ratio_poster/public/p2929760596.jpg",
        "score": "7.5",
        "region": "中国大陆",
        "rank": 4
    },
    {
        "title": "飞驰人生3",
        "link": "https://movie.douban.com/subject/37311135/?from=playing_poster",
        "image_url": "https://img9.doubanio.com/view/photo/s_ratio_poster/public/p2929427346.jpg",
        "score": "7.3",
        "region": "中国大陆",
        "rank": 5
    }
]